{"man": 19, "woman": 18, "figure": 18, "religious and ceremonial": 15, "hill": 10, "wooded": 8, "horse": 7, "cross": 6, "heating and lighting": 5, "fine arts and music": 5, "river": 5, "torch": 4, "tree": 4, "coffin": 3, "mountain": 2, "flag - non-specific": 2, "toys and models": 2, "boy": 2, "duck": 2, "lake": 2, "rainbow": 2, "gorge": 2, "scientific and measuring": 2, "hour glass": 2, "vessels and containers": 2, "basket": 2, "instrument, lute": 2, "furnishings": 1, "canopy": 1, "child": 1, "ox": 1, "sculpture": 1, "rocky": 1, "ivy": 1, "tools and machinery": 1, "ladder": 1, "field": 1, "flower": 1, "pool": 1, "sheep": 1, "agriculture, gardening & fishing": 1, "spade": 1, "canal": 1, "garland": 1, "instrument, pipe": 1, "sculpture, classical": 1, "coat of arms": 1, "clothing and personal effects": 1, "hat": 1, "headdress": 1, "instrument, bagpipes": 1, "dog - non-specific": 1, "man, old": 1, "reading, writing, printed matter": 1, "scroll": 1}