{"subject": 70, "society": 70, "lifestyle and culture": 70, "poetry": 70, "abstraction": 43, "non-representational": 38, "geometric": 27, "emotions, concepts and ideas": 17, "colour": 16, "objects": 12, "nature": 11, "formal qualities": 10, "from recognisable sources": 10, "places": 8, "people": 8, "symbols & personifications": 8, "inscriptions": 8, "religion and belief": 8, "architecture": 7, "text": 7, "world religions": 7, "literature and fiction": 6, "adults": 6, "UK countries and regions": 5, "literature (not Shakespeare)": 5, "landscape": 5, "emotions and human qualities": 5, "monochromatic": 5, "irregular forms": 5, "universal concepts": 5, "UK cities, towns and villages": 4, "man": 4, "England": 4, "townscapes, man-made features": 4, "man-made": 4, "fine art and design, named works": 4, "animals: features": 4, "figure": 4, "Islam, Sufism": 4, "cultural identity": 4, "rhythm": 4, "UK counties": 3, "animals: mammals": 3, "groups": 3, "group": 3, "woman": 3, "named individuals": 3, "countries and continents": 3, "gestural": 3, "Islam": 3, "Rumi, Jalalu'ddin, 'Divan Shams'": 3, "poem": 3, "wing": 3, "cow": 2, "work and occupations": 2, "leisure and pastimes": 2, "music and entertainment": 2, "UK London": 2, "body": 2, "head / face": 2, "portraits": 2, "title of work": 2, "actions: postures and motions": 2, "natural phenomena": 2, "transport: water": 2, "cities, towns, villages (non-UK)": 2, "Mulchelney": 2, "Somerset": 2, "vessels and containers": 2, "landscape - non-specific": 2, "void": 2, "public and municipal": 2, "features": 2, "mysticism": 2, "clothing and personal effects": 2, "hat": 2, "Arabic text": 2, "notes and diagrams": 2, "Houshiary, Shirazeh, sculpture": 2, "universal religious imagery": 2, "angel": 2, "Caernarfon, Caernarfon Castle": 1, "Caernarfonshire and Merionethshire": 1, "Wales": 1, "Gray, Thomas, 'The Bard'": 1, "bridges and viaducts": 1, "bridge": 1, "military": 1, "castle": 1, "periods and styles": 1, "medieval": 1, "water: inland": 1, "river": 1, "valley": 1, "wooded": 1, "agriculture and fishing": 1, "farm labourer": 1, "literary": 1, "poet": 1, "fine arts and music": 1, "instrument, harp": 1, "music": 1, "singing": 1, "nostalgia": 1, "Twickenham, Pope's Villa": 1, "admiration": 1, "musical analogy": 1, "reading, writing, printed matter": 1, "book, Newman, Barnett, '18 Cantos'": 1, "number": 1, "sequence": 1, "symmetry": 1, "printed text": 1, "education, science and learning": 1, "mathematics": 1, "Apollinaire, Guillaume": 1, "individuals: male": 1, "date": 1, "word": 1, "photographic": 1, "magic and occultism": 1, "astrology": 1, "nudes": 1, "female": 1, "reclining": 1, "animals: fish and aquatic life": 1, "fish": 1, "mystery": 1, "townscape": 1, "Pasta, Giuditta Saronno": 1, "individuals: female": 1, "air": 1, "ice": 1, "water": 1, "scientific and measuring": 1, "astronomical chart": 1, "sports and games": 1, "ball": 1, "miscellaneous": 1, "crystal": 1, "furnishings": 1, "display case / vitrine": 1, "kitchen": 1, "glass": 1, "muse": 1, "opera": 1, "environment / nature": 1, "happiness": 1, "purity": 1, "times of the day": 1, "morning": 1, "boat, fishing": 1, "agriculture, gardening & fishing": 1, "fishing net": 1, "New York, Dwan Gallery": 1, "USA": 1, "Novros, David, paintings": 1, "history": 1, "arts": 1, "exhibition: 'David Novros', Dwan Gallery, 1967": 1, "jar": 1, "silence": 1, "sadness": 1, "French text": 1, "transport: land": 1, "carriage": 1, "horse": 1, "head": 1, "diagrammatic": 1, "fence": 1, "signage": 1, "shop": 1, "window": 1, "spirituality": 1, "animals: actions": 1, "flying": 1, "movement": 1, "interiors": 1, "interior - non-specific": 1, "fire": 1, "trees": 1, "tree": 1, "organic": 1, "Gravesend": 1, "Maldon": 1, "Northfleet": 1, "Whitstable": 1, "Shoreditch": 1, "UK natural features": 1, "South Downs": 1, "boat, barge": 1, "boat, sailing": 1, "tales, legends and traditional": 1, "nursery rhyme, 'Oranges and Lemons'": 1, "domestic": 1, "tile": 1, "fragmentation": 1, "texture": 1, "Roberts, David, 'Fantasy for Flute'": 1, "animals: fantastic": 1, "animal / human": 1, "monkey": 1, "actions: expressive": 1, "gesticulating": 1, "head in hand/hands": 1, "sitting": 1, "actions: processes and functions": 1, "looking / watching": 1, "humour": 1, "places of entertainment": 1, "zoo": 1, "Partum, Ewa": 1, "Poland": 1, "arts and entertainment": 1, "artist, multi-media": 1, "coat": 1, "sack": 1, "letter of alphabet": 1, "underpass": 1, "Brancusi, Constantin,sculpture,  'Endless Column'": 1, "building - non-specific": 1, "design": 1, "repetition": 1, "Beirut - non-specific": 1, "Lebanon": 1, "wall": 1, "oneness / unity of existence": 1, "sex and relationships": 1, "friendship": 1, "sex": 1}